orangebeard/Cli.py
orangebeard/OrangebeardClient.py
orangebeard/__init__.py
orangebeard/config/AutoConfig.py
orangebeard/entity/Attachment.py
orangebeard/entity/Attribute.py
orangebeard/entity/FinishStep.py
orangebeard/entity/FinishTest.py
orangebeard/entity/FinishTestRun.py
orangebeard/entity/Log.py
orangebeard/entity/LogFormat.py
orangebeard/entity/LogLevel.py
orangebeard/entity/OrangebeardParameters.py
orangebeard/entity/SUTComponent.py
orangebeard/entity/Serializable.py
orangebeard/entity/StartStep.py
orangebeard/entity/StartSuite.py
orangebeard/entity/StartTest.py
orangebeard/entity/StartTestRun.py
orangebeard/entity/Suite.py
orangebeard/entity/TestStatus.py
orangebeard/entity/TestType.py
orangebeard/entity/__init__.py
orangebeard_client-2.7.2.dist-info/licenses/LICENSE
orangebeard_client-2.7.2.dist-info/METADATA
orangebeard_client-2.7.2.dist-info/WHEEL
orangebeard_client-2.7.2.dist-info/entry_points.txt
orangebeard_client-2.7.2.dist-info/top_level.txt
orangebeard_client-2.7.2.dist-info/RECORD
