Metadata-Version: 2.4
Name: orangebeard-client
Version: 2.7.2
Summary: A python3 client for Orangebeard
Author-email: Tom Heintzberger <tom@orangebeard.io>
License-Expression: AGPL-3.0-or-later
Project-URL: Homepage, https://github.com/orangebeard-io/python-client
Project-URL: Bug Tracker, https://github.com/orangebeard-io/python-client/issues
Classifier: Programming Language :: Python :: 3
Classifier: Operating System :: OS Independent
Requires-Python: >=3.7
License-File: LICENSE
Requires-Dist: pytz
Requires-Dist: aiohttp
Dynamic: license-file
